goodboy_sqlalchemy/__init__.py
goodboy_sqlalchemy/column.py
goodboy_sqlalchemy/column_schemas.py
goodboy_sqlalchemy/mapped.py
goodboy_sqlalchemy/mapped_key.py
goodboy_sqlalchemy/messages.py
goodboy_sqlalchemy/py.typed
goodboy_sqlalchemy-0.2.5.dist-info/LICENSE
goodboy_sqlalchemy-0.2.5.dist-info/METADATA
goodboy_sqlalchemy-0.2.5.dist-info/WHEEL
goodboy_sqlalchemy-0.2.5.dist-info/RECORD
